{
    "Academic Affairs Vice President": [
        {
            "name": "Melany Amarikwa",
            "number": "a3477f3b-205a-4ead-8f38-6b296b6456f8",
            "party": "Student Action"
        },
        {
            "name": "Rizza Estacio",
            "number": "68100272-b048-45f0-ad3e-1247261d556a",
            "party": "CalSERVE"
        }
    ],
    "Executive Vice President": [
        {
            "name": "Hung Huynh",
            "number": "0dac6025-a81c-4a44-b174-e96644ed4831",
            "party": "Student Action"
        },
        {
            "name": "Derek Topper",
            "number": "7d64bcfe-7768-4532-b2e4-0c616f339320",
            "party": "Independent"
        }
    ],
    "External Affairs Vice President": [
        {
            "name": "Derek Topper",
            "number": "c72252a3-d59b-45ab-a927-2143803e524c",
            "party": "Independent"
        },
        {
            "name": "Nuha Khalfay",
            "number": "1519e743-604f-4d97-8b24-d5959fd2faba",
            "party": "CalSERVE"
        }
    ],
    "President": [
        {
            "name": "Stephanie Gutierrez",
            "number": "3669f237-89f1-4626-8fde-7d9525e96fe0",
            "party": "DAAP"
        },
        {
            "name": "guutaa regassa",
            "number": "0eeec8b8-117f-4bd1-bec1-6ae32dd084d5",
            "party": "Independent"
        },
        {
            "name": "Alexander Wilfert",
            "number": "02b43f40-6ae2-4cc0-8a45-848310d938d9",
            "party": "Student Action"
        },
        {
            "name": "Juniperangelica Cordova",
            "number": "20459e2e-8938-4388-9ff0-0ee716a212fb",
            "party": "CalSERVE"
        }
    ],
    "Senator": [
        {
            "name": "Billy Allocca",
            "number": "cfec9a63-66ed-40af-a7ec-ca6e6cc73e9f",
            "party": "Independent"
        },
        {
            "name": "Aaron Bryce \"Moon Young\" Lee",
            "number": "6e6b1582-e9f6-4477-810f-e79310dc77a2",
            "party": "Independent"
        },
        {
            "name": "Jose Reyes-Hernandez",
            "number": "2648e16d-8168-4b09-a7c8-86adf397073a",
            "party": "Independent"
        },
        {
            "name": "Regina Kim",
            "number": "673662d1-e5f2-4008-8584-afbf230112db",
            "party": "Independent"
        },
        {
            "name": "Imran Khan",
            "number": "c35d9fa0-8c66-4588-8d8e-df5e4b1dcce0",
            "party": "Independent"
        },
        {
            "name": "Ishan Sharma",
            "number": "a4e8f7d1-d74c-4c72-9280-158f808c4402",
            "party": "Independent"
        },
        {
            "name": "Stephanie Luna-Lopez",
            "number": "723410dd-e4da-4d3a-aee5-7cde6c840b66",
            "party": "Independent"
        },
        {
            "name": "Ashley Nelson",
            "number": "e2d29a7c-3540-4706-bea4-dac33c128558",
            "party": "Independent"
        },
        {
            "name": "furry boi",
            "number": "131c219e-1e78-478a-8472-e1062ed06302",
            "party": "Independent"
        },
        {
            "name": "Anna Whitney",
            "number": "4ca12ed0-127e-4125-b07b-0780d34a58b8",
            "party": "Independent"
        },
        {
            "name": "Nelson Ke",
            "number": "3c9bf067-4ca7-4f1e-8e18-f8d41b4da625",
            "party": "Independent"
        },
        {
            "name": "Nick Araujo",
            "number": "c064b5b8-41e4-4b05-9d90-74f27906acda",
            "party": "Independent"
        },
        {
            "name": "Stephanie Gutierrez",
            "number": "bd6b96a8-f121-4529-848c-a1a5158bbc25",
            "party": "DAAP"
        },
        {
            "name": "Casey Leeds",
            "number": "6e8e60a0-167d-444b-b3b3-047c406a2bb9",
            "party": "DAAP"
        },
        {
            "name": "Mary Carrasco",
            "number": "c550c023-18ec-4156-ad14-c7aefe62a691",
            "party": "DAAP"
        },
        {
            "name": "Richard Alvarado",
            "number": "e5e57a34-bb6b-4044-ade9-f09a16da0a50",
            "party": "DAAP"
        },
        {
            "name": "Andy Theocharous",
            "number": "9fb7a621-94eb-4fc0-bef5-53027ae04c04",
            "party": "Student Action"
        },
        {
            "name": "James Li",
            "number": "f913d313-0807-448d-b227-40321db485b3",
            "party": "Student Action"
        },
        {
            "name": "Isabella Chow",
            "number": "3408c80b-6065-4b1d-91d4-ece904e8ba1f",
            "party": "Student Action"
        },
        {
            "name": "Karina Sun",
            "number": "8339d873-783e-43e9-a065-b51ebcffc8a1",
            "party": "Student Action"
        },
        {
            "name": "Stephanie Cong",
            "number": "76263278-2091-4b67-886d-e9774b533052",
            "party": "Student Action"
        },
        {
            "name": "Nikhil Harish",
            "number": "c788faf3-038f-4468-9b0b-de38d37f3e2d",
            "party": "Student Action"
        },
        {
            "name": "Justin Greenwald",
            "number": "0ba99646-90e1-48be-ae21-5a6c974251c7",
            "party": "Student Action"
        },
        {
            "name": "Amma Sarkodee-Adoo",
            "number": "e7d23412-11ba-4253-98da-bae531324525",
            "party": "Student Action"
        },
        {
            "name": "Neil McClintick",
            "number": "aae72f96-bfe9-4a83-959c-d8f9127cc31e",
            "party": "Student Action"
        },
        {
            "name": "Anne Zepecki",
            "number": "62010aac-9127-49c1-a512-b14ea5044de8",
            "party": "Student Action"
        },
        {
            "name": "Gabriel Louis-Kayen",
            "number": "3107e998-1a4f-49d4-8f84-d215d28c240d",
            "party": "Student Action"
        },
        {
            "name": "William Wang",
            "number": "f681bc46-3fcf-496e-ad7e-eecd128f787f",
            "party": "Student Action"
        },
        {
            "name": "Zach Carter",
            "number": "9c9e3e35-2437-4f36-b7d5-01c90e94e555",
            "party": "Student Action"
        },
        {
            "name": "Saakshi Goel",
            "number": "0ebe17ef-b64b-46a3-9a91-82efa5d44cd2",
            "party": "Student Action"
        },
        {
            "name": "Amir Wright",
            "number": "a52f0f51-4321-414f-8abd-c04d7a7d4dbb",
            "party": "CalSERVE"
        },
        {
            "name": "Sarah Abdeshahian",
            "number": "996cb453-06f7-4911-889f-07008e566932",
            "party": "CalSERVE"
        },
        {
            "name": "Tashie Williams-Powell",
            "number": "da275990-0d04-4b45-84ea-8db447647d06",
            "party": "CalSERVE"
        },
        {
            "name": "Teddy Lake",
            "number": "2fa2721e-8bea-43b1-b681-15fc0a5e6d96",
            "party": "CalSERVE"
        },
        {
            "name": "Idalys Perez",
            "number": "d68385e6-307d-4a4f-ba57-adba0f0a5454",
            "party": "CalSERVE"
        },
        {
            "name": "Justin Illescas",
            "number": "0ece80d0-d4b4-4a2a-adf2-e31af5d94845",
            "party": "CalSERVE"
        },
        {
            "name": "Angelica Santos",
            "number": "d51247b0-bac6-4f5d-92b7-5b0fba81c435",
            "party": "CalSERV"
        }
    ],
    "Student Advocate": [
        {
            "name": "Casey Leeds",
            "number": "fc5b0225-d72d-49e8-87df-aca8af50b3f2",
            "party": "DAAP"
        },
        {
            "name": "Sophie Bandarkar",
            "number": "e0019737-45af-4bc7-9e99-93922c4b6a8f",
            "party": "Independent"
        }
    ]
}