{
    "senate": [
        {
            "name": "Daniel Hernandez",
            "number": "f1093a5c-8137-4015-bdf1-ae7751ec2b08",
            "party": "Unknown"
        },
        {
            "name": "Teresa Yang Lam",
            "number": "4c23ca97-65ab-42eb-8471-6cfce7e0b71d",
            "party": "Unknown"
        },
        {
            "name": "Kim Helen Quach",
            "number": "ac5ac4bb-f259-4eb1-865c-bf5dccc91bd9",
            "party": "Unknown"
        },
        {
            "name": "Samuel Doolittle",
            "number": "65696483-7059-4019-b27c-9ac2cbec4ce8",
            "party": "Unknown"
        },
        {
            "name": "Valeria Duenas",
            "number": "73eaf470-ea06-4bdd-b015-00515e4b7c2f",
            "party": "Unknown"
        },
        {
            "name": "Ko Ser Lu Htoo",
            "number": "7e56db9e-657d-40ce-8e4e-5daee039d90d",
            "party": "Unknown"
        },
        {
            "name": "Luke Aubrey Stocker",
            "number": "d9c039b9-a767-4787-a4c1-9581e22eae0a",
            "party": "Unknown"
        },
        {
            "name": "Atanas Spasov",
            "number": "67c218ae-2fae-4d2b-aad9-50a2dfd24654",
            "party": "Unknown"
        },
        {
            "name": "Mohammad Walid Qayum",
            "number": "ed7b4dd3-7b5c-4983-ab2c-1871dd987a58",
            "party": "Unknown"
        },
        {
            "name": "Shaden Cortez",
            "number": "29b82a32-72aa-4bd0-82d9-890d2d24a2bc",
            "party": "Unknown"
        },
        {
            "name": "Lucero Vasquez",
            "number": "eb55d3cb-75d5-436b-a73b-15fb130cbb23",
            "party": "Unknown"
        },
        {
            "name": "Benjamin D. McDougall",
            "number": "48d19058-2177-4556-8ea2-bba99e465cec",
            "party": "Unknown"
        },
        {
            "name": "Brandon Clemons",
            "number": "40961d1b-44d1-4a91-99a5-464a94bab9c7",
            "party": "Unknown"
        },
        {
            "name": "Rachel Young",
            "number": "da7d7e7c-d9cb-49bb-a92f-0e11f1cc48a1",
            "party": "Unknown"
        },
        {
            "name": "Jumoke Maraiyesa",
            "number": "1e17780b-9ed8-49a8-9784-6a9158ed6286",
            "party": "Unknown"
        },
        {
            "name": "Katherine Elaine Elizabeth Weaver",
            "number": "08b07ad1-f847-44aa-a79c-7cc636d0c487",
            "party": "Unknown"
        },
        {
            "name": "Daniella Tikva Aloni",
            "number": "e4a35395-6718-4540-8620-06d726bfcd28",
            "party": "Unknown"
        },
        {
            "name": "Daniel Tillman",
            "number": "c652939a-bcc5-4a72-86b1-ef7539e5d18f",
            "party": "Unknown"
        },
        {
            "name": "Simranjit Kaur",
            "number": "7c7b3c09-8e11-44b5-94e4-7765230b045d",
            "party": "Unknown"
        },
        {
            "name": "Henna Battan",
            "number": "7229e9a1-9ae1-4e07-9dee-01fa7b26a0e7",
            "party": "Unknown"
        },
        {
            "name": "Alisha Hacker",
            "number": "9ccaa5e8-7c41-4043-8a42-142b4c31b3a5",
            "party": "Unknown"
        },
        {
            "name": "Winter 2018: Senate",
            "number": "498c5ee5-2e78-45df-9780-bce1551af359",
            "party": "Unknown"
        }
    ]
}